dep_postgres/__init__.py
pyproject.toml
tests/__init__.py
tests/test_dep_module_postgres.py
dep_module_postgres-2.2.27.dist-info/WHEEL
dep_module_postgres-2.2.27.dist-info/METADATA
dep_module_postgres-2.2.27.dist-info/RECORD
