Metadata-Version: 2.1
Name: dep-module-postgres
Version: 2.2.27
Summary: 
Author: everhide
Author-email: i.tolkachnikov@gmail.com
Requires-Python: >=3.9.0,<=3.9.13
Classifier: Programming Language :: Python :: 3
Classifier: Programming Language :: Python :: 3.9
Requires-Dist: SQLAlchemy (>=1.4.40,<2.0.0)
Requires-Dist: asyncpg (>=0.26.0,<0.27.0)
Requires-Dist: dep-spec (>=2.2.27,<3.0.0)
Requires-Dist: poetry (==1.1.15)
